funresponses/__init__.py
funresponses/fun.py
fun_responses-1.0.2.dist-info/LICENSE
fun_responses-1.0.2.dist-info/METADATA
fun_responses-1.0.2.dist-info/WHEEL
fun_responses-1.0.2.dist-info/top_level.txt
fun_responses-1.0.2.dist-info/RECORD
