Metadata-Version: 2.1
Name: fun-responses
Version: 1.0.2
Summary: An API for getting fun responses
Home-page: https://void206551.dev/projects/fun-responses
Author: Jason O'Donnell
Author-email: void206551@gmail.com
License: UNKNOWN
Platform: UNKNOWN
Classifier: Programming Language :: Python :: 3
Classifier: License :: OSI Approved :: MIT License
Classifier: Operating System :: OS Independent
Requires-Python: >=3.6
